swc/__init__.py
swc/swc.py
swc/swc_processor.py
swc/version.py
sw_cmd-0.0.6.dist-info/LICENSE
sw_cmd-0.0.6.dist-info/METADATA
sw_cmd-0.0.6.dist-info/WHEEL
sw_cmd-0.0.6.dist-info/entry_points.txt
sw_cmd-0.0.6.dist-info/top_level.txt
sw_cmd-0.0.6.dist-info/RECORD
