Metadata-Version: 2.1
Name: sw-cmd
Version: 0.0.6
Requires-Python: >=3.8
License-File: LICENSE
Requires-Dist: click
Requires-Dist: art
